{
  "id": "a4590c99-e57f-4e02-b9c8-a4c34bddb148",
  "prevId": "00000000-0000-0000-0000-000000000000",
  "version": "7",
  "dialect": "postgresql",
  "tables": {
    "dev-schema.email_queue": {
      "name": "email_queue",
      "schema": "dev-schema",
      "columns": {
        "id": {
          "name": "id",
          "type": "uuid",
          "primaryKey": true,
          "notNull": true,
          "default": "gen_random_uuid()"
        },
        "newsletter_id": {
          "name": "newsletter_id",
          "type": "uuid",
          "primaryKey": false,
          "notNull": true
        },
        "recipient_email": {
          "name": "recipient_email",
          "type": "varchar(255)",
          "primaryKey": false,
          "notNull": true
        },
        "recipient_name": {
          "name": "recipient_name",
          "type": "varchar(255)",
          "primaryKey": false,
          "notNull": false
        },
        "status": {
          "name": "status",
          "type": "varchar(50)",
          "primaryKey": false,
          "notNull": true,
          "default": "'pending'"
        },
        "scheduled_for": {
          "name": "scheduled_for",
          "type": "timestamp",
          "primaryKey": false,
          "notNull": true,
          "default": "now()"
        },
        "sent_at": {
          "name": "sent_at",
          "type": "timestamp",
          "primaryKey": false,
          "notNull": false
        },
        "attempts": {
          "name": "attempts",
          "type": "integer",
          "primaryKey": false,
          "notNull": true,
          "default": 0
        },
        "error_message": {
          "name": "error_message",
          "type": "varchar(500)",
          "primaryKey": false,
          "notNull": false
        },
        "batch_number": {
          "name": "batch_number",
          "type": "integer",
          "primaryKey": false,
          "notNull": true
        }
      },
      "indexes": {},
      "foreignKeys": {
        "email_queue_newsletter_id_newsletter_id_fk": {
          "name": "email_queue_newsletter_id_newsletter_id_fk",
          "tableFrom": "email_queue",
          "tableTo": "newsletter",
          "schemaTo": "dev-schema",
          "columnsFrom": [
            "newsletter_id"
          ],
          "columnsTo": [
            "id"
          ],
          "onDelete": "no action",
          "onUpdate": "no action"
        }
      },
      "compositePrimaryKeys": {},
      "uniqueConstraints": {},
      "policies": {},
      "checkConstraints": {},
      "isRLSEnabled": false
    },
    "dev-schema.event": {
      "name": "event",
      "schema": "dev-schema",
      "columns": {
        "id": {
          "name": "id",
          "type": "uuid",
          "primaryKey": true,
          "notNull": true,
          "default": "gen_random_uuid()"
        },
        "name": {
          "name": "name",
          "type": "varchar",
          "primaryKey": false,
          "notNull": true
        },
        "description": {
          "name": "description",
          "type": "varchar(255)",
          "primaryKey": false,
          "notNull": true
        },
        "date": {
          "name": "date",
          "type": "varchar(255)",
          "primaryKey": false,
          "notNull": true
        },
        "location": {
          "name": "location",
          "type": "varchar(255)",
          "primaryKey": false,
          "notNull": true
        }
      },
      "indexes": {},
      "foreignKeys": {},
      "compositePrimaryKeys": {},
      "uniqueConstraints": {},
      "policies": {},
      "checkConstraints": {},
      "isRLSEnabled": false
    },
    "dev-schema.newsletter": {
      "name": "newsletter",
      "schema": "dev-schema",
      "columns": {
        "id": {
          "name": "id",
          "type": "uuid",
          "primaryKey": true,
          "notNull": true,
          "default": "gen_random_uuid()"
        },
        "title": {
          "name": "title",
          "type": "varchar(255)",
          "primaryKey": false,
          "notNull": true
        },
        "content": {
          "name": "content",
          "type": "text",
          "primaryKey": false,
          "notNull": true
        },
        "date": {
          "name": "date",
          "type": "varchar(255)",
          "primaryKey": false,
          "notNull": true
        }
      },
      "indexes": {},
      "foreignKeys": {},
      "compositePrimaryKeys": {},
      "uniqueConstraints": {},
      "policies": {},
      "checkConstraints": {},
      "isRLSEnabled": false
    },
    "dev-schema.subscriber": {
      "name": "subscriber",
      "schema": "dev-schema",
      "columns": {
        "id": {
          "name": "id",
          "type": "uuid",
          "primaryKey": true,
          "notNull": true,
          "default": "gen_random_uuid()"
        },
        "email": {
          "name": "email",
          "type": "varchar(255)",
          "primaryKey": false,
          "notNull": true
        },
        "name": {
          "name": "name",
          "type": "varchar(255)",
          "primaryKey": false,
          "notNull": false
        },
        "subscribed": {
          "name": "subscribed",
          "type": "boolean",
          "primaryKey": false,
          "notNull": true,
          "default": true
        },
        "subscribed_at": {
          "name": "subscribed_at",
          "type": "timestamp",
          "primaryKey": false,
          "notNull": true,
          "default": "now()"
        },
        "unsubscribe_token": {
          "name": "unsubscribe_token",
          "type": "varchar(255)",
          "primaryKey": false,
          "notNull": true
        }
      },
      "indexes": {},
      "foreignKeys": {},
      "compositePrimaryKeys": {},
      "uniqueConstraints": {
        "subscriber_email_unique": {
          "name": "subscriber_email_unique",
          "nullsNotDistinct": false,
          "columns": [
            "email"
          ]
        }
      },
      "policies": {},
      "checkConstraints": {},
      "isRLSEnabled": false
    },
    "dev-schema.vendor": {
      "name": "vendor",
      "schema": "dev-schema",
      "columns": {
        "id": {
          "name": "id",
          "type": "uuid",
          "primaryKey": true,
          "notNull": true,
          "default": "gen_random_uuid()"
        },
        "name": {
          "name": "name",
          "type": "varchar",
          "primaryKey": false,
          "notNull": true
        },
        "description": {
          "name": "description",
          "type": "varchar(255)",
          "primaryKey": false,
          "notNull": true
        },
        "email": {
          "name": "email",
          "type": "varchar(255)",
          "primaryKey": false,
          "notNull": false
        },
        "phone": {
          "name": "phone",
          "type": "varchar(255)",
          "primaryKey": false,
          "notNull": false
        },
        "address": {
          "name": "address",
          "type": "varchar(255)",
          "primaryKey": false,
          "notNull": false
        },
        "services": {
          "name": "services",
          "type": "varchar(255)",
          "primaryKey": false,
          "notNull": false
        },
        "links": {
          "name": "links",
          "type": "varchar(255)",
          "primaryKey": false,
          "notNull": false
        }
      },
      "indexes": {},
      "foreignKeys": {},
      "compositePrimaryKeys": {},
      "uniqueConstraints": {},
      "policies": {},
      "checkConstraints": {},
      "isRLSEnabled": false
    }
  },
  "enums": {},
  "schemas": {
    "dev-schema": "dev-schema"
  },
  "sequences": {},
  "roles": {},
  "policies": {},
  "views": {},
  "_meta": {
    "columns": {},
    "schemas": {},
    "tables": {}
  }
}